setup.py
apps/__init__.py
apps/exercise_renderer.py
tests/__init__.py
tests/test_exercise_database.py
tests/test_exercise_rendering.py
tests/test_routine_engine.py
tests/test_user_database.py
xrsrv/__init__.py
xrsrv/exercise_database.py
xrsrv/exercise_rendering.py
xrsrv/routine_engine.py
xrsrv/type_factories.py
xrsrv/user_database.py
xrsrv.egg-info/PKG-INFO
xrsrv.egg-info/SOURCES.txt
xrsrv.egg-info/dependency_links.txt
xrsrv.egg-info/top_level.txt
xrsrv/routine_generators/__init__.py
xrsrv/routine_generators/basic_random.py
xrsrv/routine_generators/debug.py
xrsrv/routine_generators/generator_exception.py
xrsrv/routine_generators/multi_day_random.py