Metadata-Version: 1.0
Name: xrsrv
Version: 0.2.dev0
Summary: XRSRV - eXeRcise SeRVer library
Home-page: https://github.com/jessepinnell/xrsrv
Author: Jesse Pinnell
Author-email: jesse@vapid.io
License: MIT License
